[{"id":"eb8cf60f.9f1c08","type":"tab","label":"Flow 1","disabled":false,"info":""},{"id":"ce467525.044448","type":"telegram receiver","z":"eb8cf60f.9f1c08","name":"Entrada_Telegram","bot":"68dd5ded.acabf4","saveDataDir":"","filterCommands":false,"x":110,"y":180,"wires":[["5b298239.f050ec","3e52f2d9.dd174e"],[]]},{"id":"5b298239.f050ec","type":"debug","z":"eb8cf60f.9f1c08","name":"","active":true,"tosidebar":true,"console":false,"tostatus":false,"complete":"false","statusVal":"","statusType":"auto","x":310,"y":80,"wires":[]},{"id":"7f8b4eed.4a29c","type":"telegram sender","z":"eb8cf60f.9f1c08","name":"","bot":"68dd5ded.acabf4","haserroroutput":false,"outputs":1,"x":1010,"y":160,"wires":[[]]},{"id":"ad076627.cf4b18","type":"watson-assistant-v2","z":"eb8cf60f.9f1c08","name":"","service-endpoint":"https://api.us-south.assistant.watson.cloud.ibm.com/instances/0a4baa1d-4a21-44cd-93e9-ae348a8e4975","assistant_id":"37f5e908-f0fe-4f2e-853b-88f1485454f4","debug":false,"restart":false,"return_context":true,"alternate_intents":false,"multisession":true,"timeout":"","optout-learning":false,"persist-session-id":false,"x":610,"y":180,"wires":[["22443b3f.e60044","894f589a.d6b6f8"]]},{"id":"3e52f2d9.dd174e","type":"function","z":"eb8cf60f.9f1c08","name":"Prepara_Watson","func":"msg.params = {\n    \"session_id\" : msg.payload.chatId\n}\nmsg.chatId = msg.payload.chatId;\nmsg.payload = msg.payload.content;\n\n\nreturn msg;","outputs":1,"noerr":0,"initialize":"","finalize":"","libs":[],"x":350,"y":240,"wires":[["ad076627.cf4b18","8e562330.388a8"]]},{"id":"8e562330.388a8","type":"debug","z":"eb8cf60f.9f1c08","name":"","active":true,"tosidebar":true,"console":false,"tostatus":false,"complete":"true","targetType":"full","statusVal":"","statusType":"auto","x":570,"y":80,"wires":[]},{"id":"22443b3f.e60044","type":"debug","z":"eb8cf60f.9f1c08","name":"","active":true,"tosidebar":true,"console":false,"tostatus":false,"complete":"true","targetType":"full","statusVal":"","statusType":"auto","x":790,"y":80,"wires":[]},{"id":"894f589a.d6b6f8","type":"function","z":"eb8cf60f.9f1c08","name":"Prepara_Retorno","func":"msg.payload ={\n    \"content\" : msg.payload.output.generic[0].text,\n    \"type\" : 'message',\n    \"chatId\" : msg.chatId\n}\nreturn msg;","outputs":1,"noerr":0,"initialize":"","finalize":"","libs":[],"x":810,"y":220,"wires":[["7f8b4eed.4a29c"]]},{"id":"68dd5ded.acabf4","type":"telegram bot","botname":"@Bozer_1tdst_2022_bot","usernames":"","chatids":"","baseapiurl":"","updatemode":"polling","pollinterval":"300","usesocks":false,"sockshost":"","socksport":"6667","socksusername":"anonymous","sockspassword":"","bothost":"","botpath":"","localbotport":"8443","publicbotport":"8443","privatekey":"","certificate":"","useselfsignedcertificate":false,"sslterminated":false,"verboselogging":false}]